pysolr_aio.py
pysolr_aio-3.8.1.1.dist-info/LICENSE
pysolr_aio-3.8.1.1.dist-info/METADATA
pysolr_aio-3.8.1.1.dist-info/WHEEL
pysolr_aio-3.8.1.1.dist-info/top_level.txt
pysolr_aio-3.8.1.1.dist-info/RECORD
