Metadata-Version: 2.1
Name: pysolr-aio
Version: 3.8.1.1
Summary: Lightweight Python client for Apache Solr
Home-page: https://github.com/AeGean-Studio/pysolr_aio
Author: Daniel Lindsley
Author-email: daniel@toastdriven.com
License: BSD
Platform: UNKNOWN
Classifier: Development Status :: 5 - Production/Stable
Classifier: Intended Audience :: Developers
Classifier: License :: OSI Approved :: BSD License
Classifier: Operating System :: OS Independent
Classifier: Programming Language :: Python
Classifier: Topic :: Internet :: WWW/HTTP :: Indexing/Search
Classifier: Programming Language :: Python :: 3
Requires-Python: >=3.6
Requires-Dist: httpx (>=0.10.0)
Provides-Extra: solrcloud
Requires-Dist: kazoo (>=2.5.0) ; extra == 'solrcloud'
